MANIFEST.in
README.txt
setup.cfg
setup.py
docs/HISTORY.txt
docs/INSTALL.txt
docs/LICENSE.GPL
docs/LICENSE.txt
zettwerk/__init__.py
zettwerk.ui.egg-info/PKG-INFO
zettwerk.ui.egg-info/SOURCES.txt
zettwerk.ui.egg-info/dependency_links.txt
zettwerk.ui.egg-info/entry_points.txt
zettwerk.ui.egg-info/namespace_packages.txt
zettwerk.ui.egg-info/not-zip-safe
zettwerk.ui.egg-info/paster_plugins.txt
zettwerk.ui.egg-info/requires.txt
zettwerk.ui.egg-info/top_level.txt
zettwerk/ui/__init__.py
zettwerk/ui/configure.zcml
zettwerk/ui/filesystem.py
zettwerk/ui/profiles.zcml
zettwerk/ui/resources.py
zettwerk/ui/setuphandlers.py
zettwerk/ui/version.txt
zettwerk/ui/z.png
zettwerk/ui/Extensions/Install.py
zettwerk/ui/browser/__init__.py
zettwerk/ui/browser/configure.zcml
zettwerk/ui/browser/cp_view.py
zettwerk/ui/browser/interfaces.py
zettwerk/ui/browser/scripts/cp.js
zettwerk/ui/browser/ui-base/jquery-ui.custom.css
zettwerk/ui/browser/ui-base/images/ui-bg_flat_55_999999_40x100.png
zettwerk/ui/browser/ui-base/images/ui-bg_flat_75_aaaaaa_40x100.png
zettwerk/ui/browser/ui-base/images/ui-bg_glass_45_0078ae_1x400.png
zettwerk/ui/browser/ui-base/images/ui-bg_glass_55_f8da4e_1x400.png
zettwerk/ui/browser/ui-base/images/ui-bg_glass_75_79c9ec_1x400.png
zettwerk/ui/browser/ui-base/images/ui-bg_gloss-wave_45_e14f1c_500x100.png
zettwerk/ui/browser/ui-base/images/ui-bg_gloss-wave_50_6eac2c_500x100.png
zettwerk/ui/browser/ui-base/images/ui-bg_gloss-wave_75_2191c0_500x100.png
zettwerk/ui/browser/ui-base/images/ui-bg_inset-hard_100_fcfdfd_1x100.png
zettwerk/ui/browser/ui-base/images/ui-icons_0078ae_256x240.png
zettwerk/ui/browser/ui-base/images/ui-icons_056b93_256x240.png
zettwerk/ui/browser/ui-base/images/ui-icons_d8e7f3_256x240.png
zettwerk/ui/browser/ui-base/images/ui-icons_e0fdff_256x240.png
zettwerk/ui/browser/ui-base/images/ui-icons_f5e175_256x240.png
zettwerk/ui/browser/ui-base/images/ui-icons_f7a50d_256x240.png
zettwerk/ui/browser/ui-base/images/ui-icons_fcd113_256x240.png
zettwerk/ui/locales/zettwerk.ui.pot
zettwerk/ui/locales/de/LC_MESSAGES/zettwerk.ui.mo
zettwerk/ui/locales/de/LC_MESSAGES/zettwerk.ui.po
zettwerk/ui/locales/en/LC_MESSAGES/zettwerk.ui.mo
zettwerk/ui/locales/en/LC_MESSAGES/zettwerk.ui.po
zettwerk/ui/locales/es/LC_MESSAGES/zettwerk.ui.mo
zettwerk/ui/locales/es/LC_MESSAGES/zettwerk.ui.po
