Metadata-Version: 1.1
Name: zettwerk.ui
Version: 2.0
Summary: Adding jquery.ui's themeroller to plone 4 for easy theme customization.
Home-page: http://www.zettwerk.com
Author: Jörg Kubaile / zettwerk GmbH
Author-email: jk@zettwerk.com
License: GPL
Keywords: plone,theme,jquery,jquery.ui,themeroller
Platform: UNKNOWN
Classifier: Framework :: Plone
Classifier: Programming Language :: Python
